{
    "id": 22459,
    "document_type": "method",
    "code": "toUpperCase",
    "data": {
        "id": 22459,
        "code": "toUpperCase",
        "name": "Mayúsculas",
        "type": {
            "type": "string"
        },
        "isActive": true,
        "language": "groovy",
        "parentType": {
            "type": "string"
        },
        "sourceCode": "return self.toUpperCase();",
        "description": "",
        "package_code": "angie.core",
        "renderTemplate": "Mayúsculas",
        "complexityLevel": 1,
        "package_version": "1.0.0",
        "sourceCodeForBinaryOperator": ""
    },
    "package_code": "angie.core",
    "package_version": "1.0.0"
}